Metadata-Version: 1.0
Name: soso-distributions
Version: 0.1
Summary: Gaussian distributions
Home-page: UNKNOWN
Author: Sogbeye Oloju
Author-email: soclassique@yahoo.com
License: UNKNOWN
Platform: UNKNOWN
